[{"text":"Blood is thicker than _.","pick":1},{"text":"Donna, pick up my dry cleaning and get my wife something for Christmas. I think she likes _.","pick":1},{"text":"Here's what you can expect for the new year.\nOut: _.\nIn: _.","pick":2},{"text":"It's beginning to look a lot like _.","pick":1},{"text":"Jesus performed the miracle of _ but it was never recorded.","pick":1},{"text":"This holiday season, Tim Allen must overcome his fear of _ to save Christmas.","pick":1},{"text":"What's the one thing that makes an elf instantly ejaculate?","pick":1}]