[{"text":"A box with magazines containing strong pornography."},{"text":"A Canadian tuxedo."},{"text":"A Diet Coke that tastes like balls are in it."},{"text":"A fridge festooned with nude photos of every family member."},{"text":"A good old-fashioned skullfucking."},{"text":"A hilarious failed suicide attempt."},{"text":"A Holocaust blooper reel."},{"text":"A horny hive mind."},{"text":"A male figure skater with a massive bulge."},{"text":"A monkey fucking a coconut."},{"text":"A negative HIV test bought on Amazon."},{"text":"A Norwegian-style sweater with a cute reindeer swastika pattern."},{"text":"A sprinkle of the finest crystal meth on the eyeballs."},{"text":"A toothless hooker."},{"text":"A touching moment between a wealthy old woman and her Mexican gardener."},{"text":"A water pistol loaded with LSD."},{"text":"All this weed I found."},{"text":"An acute heroin addiction."},{"text":"Another goddamn virus from surfing questionable porn."},{"text":"Anyone that isn't me."},{"text":"Asking your best friend to hold your cock at the urinal so you can keep watching funny cat videos."},{"text":"Being bullied by a small child."},{"text":"Being one bad motherfucker."},{"text":"Beliebiers."},{"text":"Bottomless mimosas."},{"text":"Bringing five thousand $1 bills to a seventh-grade beauty pageant."},{"text":"Britney Spears circa 2007."},{"text":"Building a wall and making the Mexicans pay for it."},{"text":"Cajuns."},{"text":"Capitalism."},{"text":"Chanting \"heritage, not hate\" as you hang several black men from trees."},{"text":"CHICKENFUCKER!"},{"text":"Coffee so black that it starts picking cotton."},{"text":"Doing karate in the garage."},{"text":"Donald Trump's third nipple."},{"text":"Dried-up pulverized spunk."},{"text":"Dropping warheads on foreheads."},{"text":"Elton John's sunglass collection."},{"text":"Falling and not being able to get back up."},{"text":"Getting really high with your pet dog."},{"text":"Giving a coat hanger as a gift at a baby shower."},{"text":"Going to Hell."},{"text":"Harajuku Girl prostitutes."},{"text":"Having a pulse and being fuckable."},{"text":"I refuse to dignify that with a response."},{"text":"Ignorance and self-righteousness."},{"text":"Insulting Santa Claus."},{"text":"Justin Timberlake's cornrows."},{"text":"Killing a prostitute to get the money back."},{"text":"Killing someone."},{"text":"Kurt Cobain's shotgun."},{"text":"LOUD NOISES!"},{"text":"Making Helen Keller moan so loudly, even she can hear it."},{"text":"No comment."},{"text":"Oh, God, why?"},{"text":"Pulling a Mulan."},{"text":"Rape being perfectly acceptable as long as it was enjoyed by everyone."},{"text":"Resting your balls on the dining room table."},{"text":"Rubbing Oprah's belly until it falls asleep."},{"text":"Screaming at a deaf child."},{"text":"Sexy sport tops."},{"text":"Shooting amateur porn at the retirement home."},{"text":"Slapping strangers in the face with a porterhouse steak."},{"text":"Smelly cat, smelly cat."},{"text":"Some band you've never heard of."},{"text":"Steve Buscemi and Rebel Wilson's love child."},{"text":"Sucking on an elf's surprisingly large candy cane."},{"text":"Taking a dump in a ball pit."},{"text":"Thanks, Obama!"},{"text":"The ability to embarrass a teen anytime, anywhere"},{"text":"The alpha male."},{"text":"The awkwardness of third wheels."},{"text":"The Foo Fighters."},{"text":"The last US citizen who is not disturbingly obese."},{"text":"The Pillsbury Doughboy blowing his load all over a toaster strudel."},{"text":"The pure shock of finding out your daughter is pregnant ... and the baby is yours."},{"text":"Tyra Bank's fat years."},{"text":"Umbilical-cord handcuffs."},{"text":"Voting for Trump."},{"text":"William Shatner speaking fluently."}]