[{"text":"200 years of slavery."},{"text":"A cloud of ash that darkens the Earth for a thousand years."},{"text":"A protracted siege."},{"text":"A vague fear of something called ISIS."},{"text":"All the poop inside of my body."},{"text":"Being replaced by a robot."},{"text":"Blockbuster late fees up the wazoo."},{"text":"Building a ladder of hot dogs to the moon."},{"text":"Ebola."},{"text":"Harnessing the miraculous power of the atom to slaughter 200,000 Japanese people."},{"text":"Reading an entire book."},{"text":"Rising sea levels consistent with scientific predictions."},{"text":"Rock music and premarital sex."},{"text":"Small-town cops with M-4 assault rifles."},{"text":"The 9,000 children who starved to death today."},{"text":"The Bowflex Revolution."},{"text":"The diminishing purity of the white race."},{"text":"The dying breath of the last human."},{"text":"The events depicted in James Cameron's Avatar."},{"text":"The Great Lizard Uprising of 2352."},{"text":"The transience of all things."},{"text":"This groovy new thing called LSD."},{"text":"Trying to feel something, anything."},{"text":"What remains of my penis."}]