[{"text":"_ gets me all hot and bothered.","pick":1},{"text":"_ is a bad idea. The More You Know ...","pick":1},{"text":"_ is totally acceptable. If you're a freak.","pick":1},{"text":"_ was my old college nickname.","pick":1},{"text":"_. #squadgoals","pick":1},{"text":"_. #whitepeopleproblems","pick":1},{"text":"_. Sounds like something Cartman would like.","pick":1},{"text":"_. Yeah, I'll blame that on the dog.","pick":1},{"text":"\"The pursuit of _,\" starring Will Smith.","pick":1},{"text":"A bottle of tequila + _ = A Night to Remember.","pick":1},{"text":"Babe, come over, I'm _.","pick":1},{"text":"Charlie Sheen holds the record for _ the fastest.","pick":1},{"text":"Dammit, I don't care what anyone thinks! I'm in love with _.","pick":1},{"text":"Don't you dare fuck with _.","pick":1},{"text":"Every time a bell rings, an angel gets _.","pick":1},{"text":"I got a pop-up book entitled \"_\" for my 9-year-old nephew's birthday.","pick":1},{"text":"No sleep til' _.","pick":1},{"text":"Now this is a story all about _.","pick":1},{"text":"Ooo, daddy like _.","pick":1},{"text":"Ronda Rousey gets thoroughly arouse by _.","pick":1},{"text":"WHAT ARE THOSE?!?!?!","pick":1},{"text":"What did I used to sell to people door-to-door?","pick":1},{"text":"What do you feel when bae friend-zones you?","pick":1},{"text":"What does Hulk Hogan scream whilst ejaculating?","pick":1},{"text":"What is my most treasured memory?","pick":1},{"text":"What makes me moist.","pick":1},{"text":"What touched me in a new way?","pick":1},{"text":"What was Mother Teresa's favorite memory whilst on her pilgrimage to Ireland?","pick":1},{"text":"What was the theme of Rob Ross's most cherished painting?","pick":1},{"text":"What's the most annoying thing I need to do once or twice a week?","pick":1},{"text":"_ has been scientifically proven to cause cancer.","pick":1},{"text":"_. The best way to spice up your sex life.","pick":1},{"text":"Amazingly, Japanese toy manufacturers have managed to make _ irresistibly cute.","pick":1},{"text":"Bankrupt governments around the world are turning to _ to generate additional revenue.","pick":1},{"text":"Brace yourselves, _ is coming.","pick":1},{"text":"Christian Dior's radical new perfume was inspired by the smell of _.","pick":1},{"text":"Don't Google _. You're gonna regret it.","pick":1},{"text":"Drunk Me bought _ online. Sober Me says thanks!","pick":1},{"text":"Exposure to _ scarred me for life.","pick":1},{"text":"For your crimes against the people, I hereby sentence you to _.","pick":1},{"text":"Friends don't let friends try _.","pick":1},{"text":"I blew all my money on _.","pick":1},{"text":"I tried baking a cake, but the directions were unclear. I ended up with _.","pick":1},{"text":"I was no surprised to see _ at the trailer park.","pick":1},{"text":"In war, there is no substitute for _.","pick":1},{"text":"It's dangerous to go alone! Take _.","pick":1},{"text":"Kids, don't talk to strangers. Especially the ones who try to give you _.","pick":1},{"text":"My fortune cookie said: \"_ is in your future.\"","pick":1},{"text":"My shrink told me _ would broaden my horizons.","pick":1},{"text":"Nobody knows how, or why, _ became wildly popular in Iceland.","pick":1},{"text":"Pixar had to cut _ from their latest movie in order to keep it G-rated.","pick":1},{"text":"Straight outta _.","pick":1},{"text":"Video games taught me important lessons about _.","pick":1},{"text":"What did I regrettably buy from a street vendor?","pick":1},{"text":"What do I not want to find in my Hot Pocket.","pick":1},{"text":"What is Helen Keller surprisingly good at?","pick":1},{"text":"What made things awkward during the orgy?","pick":1},{"text":"What's my fantasy?","pick":1},{"text":"You like my cupcakes? I made them myself. The secret ingredient is _.","pick":1},{"text":"You. Me. _. Now.","pick":1},{"text":"_ broke six of my ribs.","pick":1},{"text":"_ broke six of my ribs.","pick":1},{"text":"_ in your car triples your chance of being pulled over.","pick":1},{"text":"_ should be taught in schools.","pick":1},{"text":"\"I'm sorry, Mario, but our princess is _.\"","pick":1},{"text":"Authorities were baffled when they found out the killer was actually _ all along.","pick":1},{"text":"Call of Duty: Modern _.","pick":1},{"text":"Controversy erupted when the Pope gave his blessing to _.","pick":1},{"text":"Disney's experimental amusement park centered around the theme of _ was a colossal failure.","pick":1},{"text":"Experts agree: The global financial crisis was caused by _.","pick":1},{"text":"Hello. I'd like to order a large cheese pizza and a side of _, please.","pick":1},{"text":"I can't believe they actually made \"_ For Dummies.\"","pick":1},{"text":"I can't stop myself, I just have to eat _!","pick":1},{"text":"I have a restraining order that prevents me from coming within 500 feet of _.","pick":1},{"text":"I made it halfway through _ before falling asleep","pick":1},{"text":"If you get toys from a Happy Meal, what would you get from a Sad Meal?","pick":1},{"text":"Jesus's guilty pleasure was _.","pick":1},{"text":"Kids these days have no respect for _.","pick":1},{"text":"Last April Fools Day, my friends went too far with _.","pick":1},{"text":"Mike Tyson + _ = Instant YouTube hit.","pick":1},{"text":"My New Year's resolution is to stop _.","pick":1},{"text":"Never gonna give _ up.","pick":1},{"text":"Oprah Winfrey surprised her audience by giving everyone _.","pick":1},{"text":"Paper beats Rock, Rock beats Scissors, Scissors beat Paper, and _ beats all of them.","pick":1},{"text":"Protip: \"Hey, let me show you _!\" is not a good pickup line.","pick":1},{"text":"Rumor has it that the Oval Office has a bit red button labeled \"_.\"","pick":1},{"text":"Superman's other lesser-known weakness is _.","pick":1},{"text":"What's one new thing everyone should try before taking a shower?","pick":1},{"text":"You'll understand _ when you're older.","pick":1},{"text":"Your charitable contribution will help provide clothing, food, and clean water to _.","pick":1},{"text":"_ can help any relationship","pick":1},{"text":"_ showed us that _ is a great homemade hangover remedy.","pick":2},{"text":"_: Boil 'em, mash 'em, stick 'em in a stew.","pick":1},{"text":"_. No homo.","pick":1},{"text":"\"I have _.\" - Dr. Martin Luther King Jr.","pick":1},{"text":"A fortune teller said my life would be filled with _.","pick":1},{"text":"After suffering in agony for eight millennia in Hell, my penis split open and _ flew out.","pick":1},{"text":"Ah! Your rival! What was his name again?","pick":1},{"text":"As a parent, I get excited about _.","pick":1},{"text":"As your commanding officer, I order you to perform _ for my amusement.","pick":1},{"text":"Because of my investment in Bitcoin, soon I'll be able to afford _.","pick":1},{"text":"Calm down, dear, it's only _.","pick":1},{"text":"Christmas was ruined for me when my Uncle Larry got me _.","pick":1},{"text":"Drop the kids off, call in sick, then hurry home to enjoy _.","pick":1},{"text":"Here's the draw: $1,000,000 every week for the rest of your life. Here's the catch: You're involved with _ for the rest of your life.","pick":1},{"text":"Heroin: a proud supporter of _.","pick":1},{"text":"I just received the report from the doctor. Turns out I have _.","pick":1},{"text":"I like my coffee like I like my men: filled with _.","pick":1},{"text":"I peeled the banana like I always did, but this time I found _ inside it.","pick":1},{"text":"In an exclusive CNN interview, the Pope revealed his new hobby: _.","pick":1},{"text":"Introducing powdered _! Simply add water to activate.","pick":1},{"text":"Let's do _ again! This is fun!","pick":1},{"text":"My best friend died texting while driving. The last text she sent before crashing was about _.","pick":1},{"text":"The best Christmas present Grandma ever gave was _.","pick":1},{"text":"The hills are alive, with the sound of _!","pick":1},{"text":"The last thing you will see before you die: _.","pick":1},{"text":"The root of all evil? _.","pick":1},{"text":"This Thanksgiving, I'm most thankful for _.","pick":1},{"text":"Yes, Mr. Death ... I'll play your game! But not chess! My game is _.","pick":1},{"text":"You have 72 hours to deliver the gold, or you'll face _.","pick":1}]